README.rst
setup.py
eukalypse/__init__.py
eukalypse/eukalypse.py
eukalypse/eukalypse_now.py
eukalypse/screenshot.js
eukalypse.egg-info/PKG-INFO
eukalypse.egg-info/SOURCES.txt
eukalypse.egg-info/dependency_links.txt
eukalypse.egg-info/not-zip-safe
eukalypse.egg-info/requires.txt
eukalypse.egg-info/top_level.txt