Metadata-Version: 1.1
Name: eukalypse
Version: 0.1.3
Summary: Compare websites to images of websites and spots the difference.
Home-page: https://github.com/kinkerl/eukalypse
Author: Dennis Schwertel
Author-email: s@digitalkultur.net
License: MIT
Platform: UNKNOWN
Classifier: Development Status :: 4 - Beta
Classifier: Environment :: Web Environment
Classifier: Intended Audience :: Developers
Classifier: Operating System :: OS Independent
Classifier: Programming Language :: Python
